Workbook

Sheet P1_PROBE_VOC
A1: Complaint | B1: Root Pain | C1: Pain rating (1-5) | D1: Emotional Intensity (1-5) | E1: Priority Score (Pain x Intensity) | F1: Rank
A2: Erosion of Critical Thinking | B2: Loss of Deep Learning | C2: 5 | D2: 5 | E2: =C2*D2 -> 25 | F2: =RANK(E2,$E$2:$E$14) -> 1
A3: High dependancy on hardware | B3: not everyone have modern hardware or mobile is not enough to work on | C3: 3 | D3: 3 | E3: =C3*D3 -> 9 | F3: =RANK(E3,$E$2:$E$14) -> 12
A4: Tutor is not good enough | B4: tutor anxiety or platform support for tutor is not available | C4: 5 | D4: 5 | E4: =C4*D4 -> 25 | F4: =RANK(E4,$E$2:$E$14) -> 1
A5: Student lose interest to comeback | B5: Gamification or reward systems not properly introduced | C5: 5 | D5: 5 | E5: =C5*D5 -> 25 | F5: =RANK(E5,$E$2:$E$14) -> 1
A6: Parent uncertainity of student future | B6: random changes or FOMO in this AI era, worried about kids education | C6: 5 | D6: 5 | E6: =C6*D6 -> 25 | F6: =RANK(E6,$E$2:$E$14) -> 1
A7: Parent Feel alone | B7: No AI community to express the same pain they are undergoing | C7: 3 | D7: 3 | E7: =C7*D7 -> 9 | F7: =RANK(E7,$E$2:$E$14) -> 12
A8: parent dissatisfied in student performance | B8: no proper dashboard for parent to see the progress | C8: 4 | D8: 4 | E8: =C8*D8 -> 16 | F8: =RANK(E8,$E$2:$E$14) -> 8
A9: parent feel unsafe with students sharing data and ethical use of AI | B9: no proper guard rails and handling personal data in morphing, no proper sandbox environment | C9: 5 | D9: 5 | E9: =C9*D9 -> 25 | F9: =RANK(E9,$E$2:$E$14) -> 1
A10: Phsycological risk | B10: kids may establish inappropriate relation with the chatbox referring for all situation | C10: 5 | D10: 5 | E10: =C10*D10 -> 25 | F10: =RANK(E10,$E$2:$E$14) -> 1
A11: Outsourcing creativity to AI | B11: Parents feel kids let AI generate stories, art and answers instead of imagining them — the child's own voice and originality stop developing | C11: 5 | D11: 5 | E11: =C11*D11 -> 25 | F11: =RANK(E11,$E$2:$E$14) -> 1
A12: students feel uncomfortable when confronted before the class students | B12: No proper training to the teacher to make the student feel safe in the class without any judgment | C12: 4 | D12: 4 | E12: =C12*D12 -> 16 | F12: =RANK(E12,$E$2:$E$14) -> 8
A13: Return money problem is a scam | B13: no proper handling of trust in money back guarnatee | C13: 3 | D13: 4 | E13: =C13*D13 -> 12 | F13: =RANK(E13,$E$2:$E$14) -> 11
A14: class continuty missed | B14: Lack of tutor consistency, regular rescheduling of the classes | C14: 4 | D14: 4 | E14: =C14*D14 -> 16 | F14: =RANK(E14,$E$2:$E$14) -> 8
A16: Loved | B16: Underlying Desire | C16: Importance (1-5) | D16: Analyst note
A17: Gamified | B17: Student love learning by thenself when gamification is there | C17: 5 | D17: Gamification + projects + community showcase all score 5 — they reinforce each other: a rank/badge system drives return visits, projects create the thing to show, and the showcase gives parents proof.
A18: project base learning | B18: parents are proud to show what their child create | C18: 5
A19: financial literacy | B19: parents loved their children getting good at finance which is a lfe skill | C19: 3
A20: portfolio displayed as community | B20: parent love showcasing kids project and also kids inspire on seeing on other student project | C20: 5
A21: one on one session | B21: Students get individual attention | C21: 4
A28: Top 3 Pains | B28: Analyst rationale
A29: 1. Parent uncertainty about child's future in the AI era (FOMO) — score 25 | B29: The emotional trigger that makes parents search and pay. Drives the purchase.
A30: 2. Erosion of critical thinking — kids outsourcing thinking & creativity to AI — score 25 | B30: Replaced 'uncomfortable being confronted in class' (score 16). Critical-thinking loss is scored 5/5 in your own VOC, is the #1 parent fear in 2025-26 surveys (~70% of parents), and is exactly what BrainLIT's 'Mudhala Yosi — Think First' method solves. 'Safe, no-judgment class' is kept as a delivery promise (see P3).
A31: 3. Student loses interest and does not come back (drop-off) — score 25 | B31: Drives retention and membership revenue (Spark ₹999/month). Solved by rank system + weekly Yosi Challenges.
A33: Top 3 Desires
A34: 1. Project-based learning — a real thing the child built
A35: 2. Gamified progress (ranks, badges, challenges)
A36: 3. Portfolio showcased to the community (Demo Day, parents watching)
A38: Core Problem Statement:
A39: Parents in the AI era are anxious that their children will either fall behind or let AI do their thinking for them. They need a safe, engaging programme where children learn to THINK FIRST and then use AI to build real projects — with gamified progress that keeps them coming back and a visible portfolio + Demo Day that lets parents see the growth.

Sheet P2_PROFILE_COMPETITORS
A1: Competitor | B1: USP / Promise | C1: Funnels | D1: Hooks | E1: Main Offer | F1: Price | G1: CTA | H1: Weakness | I1: Price basis / Source
A2: Tynker | B2: AI + Coding for Kids — learn AI by building interactive projects, games and apps while developing critical thinking and creativity | C2: SEO → Free lessons/projects → Explore curriculum → Subscription | D2: 'AI can code but only you can innovate' | E2: Self-paced subscription with limited free lessons; 40% discount if you sign up now | F2: Quarterly ₹499.80/mo, Yearly ₹434.95/mo, Lifetime ₹13,199 one-time | G2: Join Free — lead form | H2: Self-paced — child needs constant self-motivation; no live tutor, no local language, no parent visibility beyond app | I2: Captured by owner from tynker.com (India pricing page)
A3: Create & Learn | B3: 3 big promises: expert live teachers, small classes (≤5), fun project-based curriculum designed with Google/Stanford alumni | C3: Google Ads + SEO → FREE intro class → counsellor/email nurture → quarterly pack | D3: 'Free live AI class for kids' — free intro class hook, 3.2x avg ROAS reported by their agency | E3: Small-group live classes (AI Explorers, ChatGPT for kids, Python AI), sold in terms of ~10-12 classes | F3: ≈ US$25–30 per class (≈ ₹2,100–2,500); term ≈ US$300–325 | G3: Book a FREE class; CRM + lead form + WhatsApp follow-up | H3: US-timezone/US pricing — expensive for Indian parents; English-only; AI taught as tech skill, not thinking skill | I3: create-learn.us; codecompasskids.com review 2026
A4: Code.org / CodeA | B4: Free, standards-aligned CS + AI education for everyone | C4: School/teacher adoption → Hour of Code / Hour of AI campaigns → self-serve student accounts | D4: 'Hour of AI' — anyone can learn in one hour | E4: Free courses & AI lessons, mostly delivered through schools | F4: Free | G4: Start learning / Teachers sign up | H4: No live mentor, no accountability, no local-language support; parents get no progress visibility; depends on school teacher quality | I4: code.org
A5: BrightCHAMPS | B5: Live, personalised future-skills education (coding, AI, robotics, financial literacy) — 1:1 with a teacher | C5: Meta/Google ads → free trial class → sales counsellor call → class-pack upsell | D5: 'Free 1:1 trial class' + fear-of-missing-out on future skills | E5: 1:1 live class packs (Gen-AI for kids, coding, financial literacy); ages 6-16 | F5: ≈ US$16–25 per 60-min class (≈ ₹1,300–2,100); India pricing quote-based; packs of 10-15+ classes | G5: Book a free trial class | H5: High-pressure counsellor sales; expensive packs; tutor churn & rescheduling complaints; screen-time-heavy 1:1 with little peer community | I5: brightchamps.com; myengineeringbuddy.com review 2025
A6: Codingal | B6: AI-first coding education with projects and progression (48-lesson AI & AI/ML tracks) | C6: SEO city pages (e.g. 'coding classes in Chennai') + ads → free trial → academic counsellor | D6: 'Free trial class — no card needed'; scholarships & sibling discounts | E6: Long-term AI/coding tracks; 1:1, micro-group (2-3) or small group (4-5) | F6: Not public; premium academies ≈ ₹15,000–80,000 per term | G6: Book a free trial lesson | H6: Coding-centric — heavy for kids/parents who want thinking & AI literacy, not programming; opaque pricing; English-first | I6: codingal.com; juniorcodes.com market reference
A7: Codevidhya | B7: Personalised 1:1 coding + school implementation (Scratch to AI) | C7: B2B school partnerships + SEO → free trial class | D7: 'Personalised live coding classes' | E7: 1:1 live coding/AI classes ages 6-16 + school curriculum licensing | F7: Not public — quote after trial | G7: Book a free trial class | H7: Primarily coding syllabus; weak brand pull with parents; no community/showcase layer | I7: codevidhya.com
A8: PlanetSpark | B8: Communication & public-speaking skills for kids (English, debate, creative writing) with AI feedback | C8: Heavy Meta/YouTube ads → free trial → counsellor call | D8: 'Make your child a confident speaker' | E8: 1:1 live communication courses; annual packs | F8: ≈ ₹13,000 entry to ₹39,000 premium bundles | G8: Book a free trial class | H8: Not an AI-literacy programme; English-only; pushy sales. BUT it proves Indian parents pay for 'confidence/thinking' outcomes — BrainLIT's debate (Naan Solluvaen) overlaps here | I8: planetspark.in fee blog
A9: DIY: YouTube + free ChatGPT (substitute) | B9: Free, unlimited, on-demand | C9: Organic / algorithm | D9: Viral 'AI hacks' videos | E9: Kids self-learn AI tools | F9: Free | G9: — | H9: No structure, no safety guard-rails, no feedback — this is exactly the 'AI does my thinking' risk parents fear | I9: Analyst assessment
A12: Competitor pattern (analyst summary)
A13: 1. Everyone sells AI as a CODING / TOOL skill — nobody owns 'thinking first' in the AI era. 2. Everyone uses the same funnel: ad → FREE trial class → counsellor call → expensive pack. Parents are tired of pushy sales. 3. Nobody teaches in Tamil/Tanglish or is rooted in Tamil Nadu parents' context. 4. Weak parent visibility and no peer community/showcase — progress is invisible between classes. 5. Price anchors: ₹1,300–2,500 per live class (1:1 or small group); subscriptions ₹435–500/month self-paced.

Sheet P3_PINPOINT
A1: Feature / Expectation | B1: Competitor A: BrightCHAMPS | C1: Competitor B: Codingal | D1: Competitor C: Tynker / Create & Learn | E1: Market Wants (Y/N) | F1: Gap? | G1: BrainLIT today
A2: Teaches kids to think critically BEFORE using AI (not just tool/coding skills) | B2: No | C2: No | D2: Partial (claims it) | E2: Yes | F2: YES — core gap | G2: Yes — L.I.T. + 5 Thinking Muscles
A3: Local-language (Tamil / Tanglish) instruction | B3: No | C3: No | D3: No | E3: Yes | F3: YES — unserved | G3: Yes — Tanglish
A4: Real project + portfolio the child owns | B4: Yes | C4: Yes | D4: Yes | E4: Yes | F4: No (table stakes) | G4: Yes — 12-page portfolio + Capstone
A5: Live Demo Day where parents watch the child present | B5: No | C5: Partial | D5: No | E5: Yes | F5: YES | G5: Yes — Demo Day
A6: Parent progress visibility (weekly updates / dashboard) | B6: Partial (reports) | C6: Partial (reports) | D6: Partial (app) | E6: Yes | F6: YES — partial gap | G6: Yes — WhatsApp after every session; dashboard not yet
A7: Gamified progress that makes kids come back | B7: Partial | C7: Partial (badges) | D7: Yes | E7: Yes | F7: Partial | G7: Yes — Spark/Flame/Blaze ranks
A8: AI safety, ethics & data guard-rails taught explicitly | B8: Partial | C8: Partial | D8: Partial | E8: Yes | F8: YES | G8: Partial — Fact Detective; add safety charter
A9: Peer community / debate across cities | B9: No | C9: No | D9: No | E9: Yes | F9: YES | G9: Yes — Naan Solluvaen (membership)
A10: Consistent tutor / no rescheduling | B10: No (churn complaints) | C10: Partial | D10: Yes | E10: Yes | F10: YES | G10: Yes — founder-led small cohorts (≤15)
A11: Affordable for Tier-1/2 Indian families | B11: No | C11: No | D11: Yes (self-paced only) | E11: Yes | F11: YES | G11: Yes — ₹999/month membership
A12: Transparent pricing, no pushy counsellor call | B12: No | C12: No | D12: Yes | E12: Yes | F12: YES | G12: Yes — price stated openly
A14: Expectation | B14: Parents want their child to be future-ready with AI WITHOUT losing the ability to think, create and speak for themselves — in a safe, engaging, affordable class they can actually see progress in.
A15: Current Market Delivery | B15: Coding-first AI courses in English, sold through free-trial → counsellor pressure → costly 1:1 packs; progress mostly invisible to parents; no peer community; self-paced apps lose the child in weeks.
A16: Gap Statement | B16: No one in Tamil Nadu offers a THINK-FIRST AI programme in Tanglish that turns kids into confident thinkers and builders, with visible proof (portfolio + Demo Day) and a gamified community that keeps them coming back.

Sheet P4_POSITION
A1: Chosen Category | B1: Think-First AI Literacy for Kids (Grades 6–10) — not a coding class
A3: What competitors focus on | B3: Coding syntax and AI tools: 'learn Python / build a chatbot', certificates, and 1:1 tutor hours. They sell SKILLS and use fear of missing out, pushed through free trial → counsellor calls.
A5: My focus | B5: THINKING before tools: the L.I.T. method (Listen, Interrogate, Think Aloud) and 5 Thinking Muscles (Question, Skeptic, Context, Empathy, Courage) — then AI to build real projects. Taught in Tanglish, in small founder-led cohorts, with visible proof for parents (portfolio, Demo Day, WhatsApp updates) and a rank system + community that keeps kids coming back.
A7: Category Claim Statement | B7: BrainLIT is the THINK-FIRST AI school for Tamil kids: other courses teach children to use AI — BrainLIT teaches them to out-think it. 'Mudhala Yosi — Think First.'

Sheet P5_PROMISE (USP)
A1: WHO | B1: Tamil-speaking parents (Chennai, Coimbatore & Tier-2 TN + Gulf/Singapore diaspora) of children in Grades 6–10 (age 10–15), who worry their child will fall behind in AI — or let AI do their thinking.
A3: PROBLEM | B3: Kids are using ChatGPT to skip thinking and creativity, lose interest in classes quickly, and parents cannot see real progress — while existing AI courses are coding-heavy, English-only, and sold with pressure.
A5: OUTCOME | B5: In 9 live sessions the child becomes a confident, questioning thinker who builds a real AI Capstone project, presents it live at Demo Day, and leaves with a 12-page portfolio and a Spark rank — and wants to continue.
A7: MECHANISM | B7: The L.I.T. Method (Listen → Interrogate → Think Aloud) training 5 Thinking Muscles, delivered in Tanglish, in small founder-led cohorts (≤15), with weekly Yosi Challenges, a gamified rank system (Spark → Flame → Blaze) and a parent WhatsApp update after every session.
A10: Final USP Sentence | B10: I help Tamil-speaking parents of 10–15 year-olds solve the fear that AI will do their child's thinking, to achieve a confident thinker who builds and presents real AI projects, using the Tanglish L.I.T. 'Think First' method (Listen, Interrogate, Think Aloud).
A11: I help ____ solve ____ to achieve ____ using ____
A12: Short USP / tagline | B12: Other courses teach kids to USE AI. BrainLIT teaches them to OUT-THINK it — in Tanglish.
A13: Tanglish tagline | B13: Mudhala Yosi — aprom AI. (Think first — then AI.)

Sheet P6_PROOF
A1: Proof Type | B1: Description | C1: Strength (1-5) | D1: Action to strengthen (next 30 days)
A2: Testimonials | B2: Cohort 1 (May 2026) parents and children — Demo Day reactions, 'Before BrainLIT I ___, Now I ___' video compilation | C2: 3 | D2: Collect 5 short parent video testimonials (30-60 sec, in Tamil/Tanglish) with the child's Capstone on screen. Ask right after Demo Day moments.
A3: Metrics / Results | B3: Cohort 1: 9-session cohort, Demo Day, per-child Life OS portfolios. Not yet measured: completion %, membership conversion %, before/after thinking score | C3: 2 | D3: Publish 3 numbers: session attendance %, Demo Day presentation %, Spark membership conversion %. Add a simple before/after 'Thinking Muscle' self-rating.
A4: Clients / Brands | B4: Student work from named schools (e.g. Narayana e-Techno, Chennai Public School) in Life OS portfolios; webinar registrants across TN cities | C4: 2 | D4: Get written permission to show 'kids from X schools'; pursue 1-2 school workshop partnerships (CBSE CT & AI curriculum from 2026-27 is the opening).
A5: Guarantee / Risk Reversal | B5: Proposed: 'Attend the first 2 sessions — if your child is not excited to come back, full refund, no questions.' Membership: cancel any month. | C5: 4 | D5: Make it simple and written; pay refunds within 48 hours (VOC shows parents distrust money-back claims — speed builds trust).
A6: Demonstration / Artifacts | B6: Children's Capstones, AI storybooks, debate videos (Naan Solluvaen), AI Identity Cards — shareable on Instagram/WhatsApp | C6: 4 | D6: Build a public 'BrainLIT Wall' (Instagram highlight + web page) of 20 child projects with parent consent.
A7: Founder / Authority | B7: Founder-led (Haja) — designed L.I.T. framework & 5 Thinking Muscles; personally teaches every cohort | C7: 3 | D7: Record a 3-min founder story video: why 'Think First'; speak at 2 school PTA meetings.
A9: Average proof strength | B9: Scores are analyst estimates (1-5) based on proof that exists today, not proof planned. | C9: =AVERAGE(C2:C7) -> 3
A10: Weakest proof type | C10: =INDEX(A2:A7,MATCH(MIN(C2:C7),C2:C7,0)) -> Metrics / Results

Sheet P7_PILOT
A1: Headline (USP) | B1: Other AI courses teach your child to USE AI. BrainLIT teaches them to OUT-THINK it — in Tanglish. | C1: Test variants
C2: A — Fear: 'Is ChatGPT doing your child's homework… and their thinking?' B — Pride: 'My 11-year-old built this and presented it live.' (Demo Day clip) C — Identity: 'Mudhala Yosi — Think First. AI class in Tanglish.'
A3: CTA | B3: Book a FREE 45-min 'AI vs Me' live class (Saturday 5 PM) — WhatsApp 'YOSI' to join
A5: Platform | B5: Meta (Instagram Reels + Facebook feed, TN + Gulf targeting) and Google Search ('AI class for kids Chennai'); WhatsApp as the reply channel
A7: Views | B7: 10000
A9: Clicks / Replies | B9: 250
A11: Conversion % | B11: =IF(B7>0,B9/B7,0) -> 0.025
A12: Free-class sign-ups (target) | B12: 40
A13: Notes | B13: Run 3 creatives (col C) for 7 days at equal budget. Winner = lowest cost per free-class sign-up, not most views. Pass if CTR ≥ 1.5%, cost per sign-up ≤ ₹150, ≥ 20% of free-class attendees enrol. Values in B7, B9, B12, B14 are TARGETS — overwrite with actuals; conversion % and cost per enrolment update automatically.
A14: Paid enrolments (target) | B14: 8
A15: Ad spend (₹) | B15: 5000
A16: Cost per enrolment (₹) | B16: =IF(B14>0,B15/B14,0) -> 625

Sheet Final Positioning 
A1: Market Pain | B1: Parents fear their child will fall behind in the AI era — or let AI do their thinking; kids lose interest in classes and parents cannot see progress.
A2: Desired Outcome | B2: A confident child who thinks first, builds and presents real AI projects, stays engaged — and a parent who can SEE the growth.
A3: Market Gap | B3: =P3_PINPOINT!B16 -> No one in Tamil Nadu offers a THINK-FIRST AI programme in Tanglish that turns kids into confident thinkers and builders, with visible proof (portfolio + Demo Day) and a gamified community that keeps them coming back.
A4: Category Claim | B4: =P4_POSITION!B7 -> BrainLIT is the THINK-FIRST AI school for Tamil kids: other courses teach children to use AI — BrainLIT teaches them to out-think it. 'Mudhala Yosi — Think First.'
A5: USP Line | B5: ='P5_PROMISE (USP)'!B10 -> I help Tamil-speaking parents of 10–15 year-olds solve the fear that AI will do their child's thinking, to achieve a confident thinker who builds and presents real AI projects, using the Tanglish L.I.T. 'Think First' method (Listen, Interrogate, Think Aloud).
A6: Proof Stack | B6: ="Cohort 1 portfolios & Demo Day videos · Children's Capstones & debate clips · 2-session refund guarantee · Founder-led small cohorts · Parent WhatsApp after every session (avg proof strength "&TEXT(P6_PROOF!C9,"0.0")&"/5)" -> Cohort 1 portfolios & Demo Day videos · Children's Capstones & debate clips · 2-session refund guarantee · Founder-led small cohorts · Parent WhatsApp after every session (avg proof strength 3.0/5)
A7: Smoke / Pilot Test Result | B7: ="Pending — test planned (targets): "&TEXT(P7_PILOT!B7,"#,##0")&" views, "&TEXT(P7_PILOT!B11,"0.0%")&" click/reply rate, "&P7_PILOT!B14&" enrolments at ₹"&TEXT(P7_PILOT!B16,"#,##0")&" each" -> Pending — test planned (targets): 10,000 views, 2.5% click/reply rate, 8 enrolments at ₹625 each
A9: Pricing position | B9: 9-session cohort, then Spark membership ₹999/month — below 1:1 players (₹1,300–2,500 per class) and above self-paced apps (₹435–500/month): 'premium community, not premium tutor'.
A10: Top 3 next actions | B10: 1. Run the 7-day smoke test (P7) and replace targets with actuals. 2. Capture 5 parent video testimonials + publish 3 Cohort-1 metrics (P6). 3. Add a parent progress dashboard/monthly report and a written AI-safety charter to close the last two gaps (P3).

Sheet Sources & Assumptions
A1: Item | B1: Source / assumption
A2: P1 VOC data | B2: Entered by owner; analyst added Priority Score formula and revised Top 3 (rationale in P1 col B).
A3: BrainLIT offer details | B3: BrainLIT Enhanced Session Facilitator Guide (Cohort 1, May 2026): L.I.T., 5 Thinking Muscles, rank system, Demo Day, Spark membership ₹999/month.
A4: Ad budget ₹5,000 | B4: 'Calculator - BrainLIT' sheet (Dec 2025).
A5: Parent concern: ~70% fear child won't learn to think critically | B5: Codeyoung parent survey — https://www.codeyoung.com/blog/parents-kids-ai-survey ; CNBC Oct 2025 — https://www.cnbc.com/2025/10/13/experts-warn-ai-llm-chatgpt-gemini-perplexity-claude-grok-copilot-could-reshape-teen-youth-brains.html
A6: CBSE CT & AI curriculum, Classes 3–8 from 2026-27 | B6: CBSE notification — https://www.cbse.gov.in/cbsenew/documents/Notification_CT_AI_2026_27_09042026.pdf
A7: BrightCHAMPS pricing | B7: https://www.myengineeringbuddy.com/blog/brightchamps-tutoring-platform-in-depth-review/ ; https://brightchamps.com/en-in/courses/gen-ai-for-kids
A8: Codingal pricing/tracks | B8: https://www.codingal.com/en-us/courses/ai-and-machine-learning/ ; https://juniorcodes.com/coding-classes-for-kids-in-bangalore
A9: Create & Learn pricing | B9: https://codecompasskids.com/create-and-learn-review/ ; https://www.create-learn.us/ai-for-kids
A10: PlanetSpark pricing | B10: https://www.planetspark.in/blogs/Understanding-PlanetSpark-Fees:-What-Makes-It-Worth-Every-Penny
A11: Codevidhya | B11: https://codevidhya.com/ai-for-kids/
A12: Tynker pricing | B12: Entered by owner (tynker.com India pricing).
... A15: Removed content | B15: P3–P7 and Final previously held a real-estate digital-marketing example (and P2 rows 17-23 an agency list). Replaced with BrainLIT analysis; original file is unchanged.
